LICENSE
MANIFEST.in
README.md
setup.cfg
setup.py
requirements/requirements.txt
src/os_netloc_rule/VERSION
src/os_netloc_rule/__init__.py
src/os_netloc_rule/netloc.py
src/os_netloc_rule.egg-info/PKG-INFO
src/os_netloc_rule.egg-info/SOURCES.txt
src/os_netloc_rule.egg-info/dependency_links.txt
src/os_netloc_rule.egg-info/not-zip-safe
src/os_netloc_rule.egg-info/top_level.txt
tests/__init__.py
tests/test_netloc.py
tests/test_version.py